{"name":"ConfigurationAdapter","isClass":false,"isInterface":true,"isEnum":false,"isEnumConstant":false,"isConstructor":false,"isField":false,"isMethod":false,"isOrdinaryClass":false,"isPrimitive":false,"simpleName":"ConfigurationAdapter","qualifiedName":"net.md_5.bungee.api.config.ConfigurationAdapter","dimension":"","elementType":{},"package":"net.md_5.bungee.api.config","interfaces":[],"isAbstract":true,"isStatic":false,"innerClasses":[],"isInnerClass":false,"constructors":[],"fields":[],"methods":[{"name":"load","isClass":false,"isInterface":false,"isEnum":false,"isEnumConstant":false,"isConstructor":false,"isField":false,"isMethod":true,"isOrdinaryClass":false,"signature":"()","flatSignature":"()","returnType":{"isPrimitive":true,"simpleName":"void","qualifiedName":"void","dimension":"","elementType":{}},"isAbstract":true,"isDefault":false,"isStatic":false,"parameters":[],"typeParameters":[]},{"name":"getInt","isClass":false,"isInterface":false,"isEnum":false,"isEnumConstant":false,"isConstructor":false,"isField":false,"isMethod":true,"isOrdinaryClass":false,"signature":"(java.lang.String, int)","flatSignature":"(String, int)","returnType":{"isPrimitive":true,"simpleName":"int","qualifiedName":"int","dimension":"","elementType":{}},"isAbstract":true,"isDefault":false,"isStatic":false,"parameters":[{"name":"path","type":{"isPrimitive":false,"simpleName":"String","qualifiedName":"java.lang.String","dimension":"","elementType":{}}},{"name":"def","type":{"isPrimitive":true,"simpleName":"int","qualifiedName":"int","dimension":"","elementType":{}}}],"typeParameters":[]},{"name":"getString","isClass":false,"isInterface":false,"isEnum":false,"isEnumConstant":false,"isConstructor":false,"isField":false,"isMethod":true,"isOrdinaryClass":false,"signature":"(java.lang.String, java.lang.String)","flatSignature":"(String, String)","returnType":{"isPrimitive":false,"simpleName":"String","qualifiedName":"java.lang.String","dimension":"","elementType":{}},"isAbstract":true,"isDefault":false,"isStatic":false,"parameters":[{"name":"path","type":{"isPrimitive":false,"simpleName":"String","qualifiedName":"java.lang.String","dimension":"","elementType":{}}},{"name":"def","type":{"isPrimitive":false,"simpleName":"String","qualifiedName":"java.lang.String","dimension":"","elementType":{}}}],"typeParameters":[]},{"name":"getBoolean","isClass":false,"isInterface":false,"isEnum":false,"isEnumConstant":false,"isConstructor":false,"isField":false,"isMethod":true,"isOrdinaryClass":false,"signature":"(java.lang.String, boolean)","flatSignature":"(String, boolean)","returnType":{"isPrimitive":true,"simpleName":"boolean","qualifiedName":"boolean","dimension":"","elementType":{}},"isAbstract":true,"isDefault":false,"isStatic":false,"parameters":[{"name":"path","type":{"isPrimitive":false,"simpleName":"String","qualifiedName":"java.lang.String","dimension":"","elementType":{}}},{"name":"def","type":{"isPrimitive":true,"simpleName":"boolean","qualifiedName":"boolean","dimension":"","elementType":{}}}],"typeParameters":[]},{"name":"getList","isClass":false,"isInterface":false,"isEnum":false,"isEnumConstant":false,"isConstructor":false,"isField":false,"isMethod":true,"isOrdinaryClass":false,"signature":"(java.lang.String, java.util.Collection\u003c?\u003e)","flatSignature":"(String, Collection\u003c?\u003e)","returnType":{"isPrimitive":false,"simpleName":"Collection","qualifiedName":"java.util.Collection","dimension":"","elementType":{}},"isAbstract":true,"isDefault":false,"isStatic":false,"parameters":[{"name":"path","type":{"isPrimitive":false,"simpleName":"String","qualifiedName":"java.lang.String","dimension":"","elementType":{}}},{"name":"def","type":{"isPrimitive":false,"simpleName":"Collection","qualifiedName":"java.util.Collection","dimension":"","elementType":{}}}],"typeParameters":[]},{"name":"getServers","isClass":false,"isInterface":false,"isEnum":false,"isEnumConstant":false,"isConstructor":false,"isField":false,"isMethod":true,"isOrdinaryClass":false,"signature":"()","flatSignature":"()","returnType":{"isPrimitive":false,"simpleName":"Map","qualifiedName":"java.util.Map","dimension":"","elementType":{}},"isAbstract":true,"isDefault":false,"isStatic":false,"parameters":[],"typeParameters":[]},{"name":"getListeners","isClass":false,"isInterface":false,"isEnum":false,"isEnumConstant":false,"isConstructor":false,"isField":false,"isMethod":true,"isOrdinaryClass":false,"signature":"()","flatSignature":"()","returnType":{"isPrimitive":false,"simpleName":"Collection","qualifiedName":"java.util.Collection","dimension":"","elementType":{}},"isAbstract":true,"isDefault":false,"isStatic":false,"parameters":[],"typeParameters":[]},{"name":"getGroups","isClass":false,"isInterface":false,"isEnum":false,"isEnumConstant":false,"isConstructor":false,"isField":false,"isMethod":true,"isOrdinaryClass":false,"signature":"(java.lang.String)","flatSignature":"(String)","returnType":{"isPrimitive":false,"simpleName":"Collection","qualifiedName":"java.util.Collection","dimension":"","elementType":{}},"isAbstract":true,"isDefault":false,"isStatic":false,"parameters":[{"name":"player","type":{"isPrimitive":false,"simpleName":"String","qualifiedName":"java.lang.String","dimension":"","elementType":{}}}],"typeParameters":[]},{"name":"getPermissions","isClass":false,"isInterface":false,"isEnum":false,"isEnumConstant":false,"isConstructor":false,"isField":false,"isMethod":true,"isOrdinaryClass":false,"signature":"(java.lang.String)","flatSignature":"(String)","returnType":{"isPrimitive":false,"simpleName":"Collection","qualifiedName":"java.util.Collection","dimension":"","elementType":{}},"isAbstract":true,"isDefault":false,"isStatic":false,"parameters":[{"name":"group","type":{"isPrimitive":false,"simpleName":"String","qualifiedName":"java.lang.String","dimension":"","elementType":{}}}],"typeParameters":[]}],"typeParameters":[],"enumConstants":[]}